MANIFEST.in
README.md
setup.py
bin/sems-start
sems/__init__.py
sems/logger.py
sems/settings.py
sems.egg-info/PKG-INFO
sems.egg-info/SOURCES.txt
sems.egg-info/dependency_links.txt
sems.egg-info/requires.txt
sems.egg-info/top_level.txt
sems/monitors/__init__.py
sems/monitors/base.py
sems/monitors/helpers.py
sems/monitors/http_status_monitor.py
sems/monitors/socket_port_monitor.py
sems/monitors/text_monitor.py
sems/repository/__init__.py
sems/repository/base.py
sems/repository/event.py
sems/repository/monitor.py
sems/server/__init__.py
sems/server/dashboard.py
sems/server/static.py
sems/server/api/__init__.py
sems/server/api/base.py
sems/server/api/events.py
sems/server/api/monitors.py
sems/server/static/bootstrap-theme.css
sems/server/static/bootstrap.css
sems/server/static/dashboard.css
sems/server/static/dashboard.js
sems/server/static/monitor.js
sems/server/static/monitor_form.js
sems/server/static/rest_client.js
sems/server/static/sortable.min.js
sems/server/templates/dashboard.html
sems/server/templates/dashboard.slim.html
sems/utils/__init__.py
tests/__init__.py
tests/test_logger.py
tests/monitors/__init__.py
tests/monitors/test_http_status_monitor.py
tests/monitors/test_socket_port_monitor.py
tests/monitors/test_text_monitor.py
tests/repository/__init__.py
tests/repository/test_event.py
tests/repository/test_monitor.py
tests/server/__init__.py
tests/server/test_dashboard.py
tests/server/api/__init__.py
tests/server/api/test_monitors.py
tests/utils/__init__.py
tests/utils/test_module.py