Metadata-Version: 1.1
Name: sems
Version: 0.0.15.0
Summary: A Simple Environment Monitor System
Home-page: http://github.com/diegorubin/simple-environment-monitor-system
Author: Diego Rubin
Author-email: rubin.diego@gmail.com
License: GPL2
Platform: UNKNOWN
Classifier: Development Status :: 3 - Alpha
